google_pandas_agent/__init__.py
google_pandas_agent/executor.py
google_pandas_agent/graph.py
google_pandas_agent/prompt.py
google_pandas_agent/tools.py
google_pandas_agent-1.0.3.dist-info/licenses/LICENSE
google_pandas_agent-1.0.3.dist-info/METADATA
google_pandas_agent-1.0.3.dist-info/WHEEL
google_pandas_agent-1.0.3.dist-info/top_level.txt
google_pandas_agent-1.0.3.dist-info/RECORD
