Metadata-Version: 2.4
Name: google-pandas-agent
Version: 1.0.3
Summary: Google‑native alternative to LangChain's create_pandas_dataframe_agent
Author-email: Ariamehr Maleki <ariamehr.mai@gmail.com>, Frank Roh <frankagilepm@gmail.com>, Darren North <denorth222@gmail.com>
License-Expression: MIT
Project-URL: Homepage, https://github.com/yourusername/google-pandas-agent
Project-URL: Documentation, https://github.com/yourusername/google-pandas-agent#readme
Project-URL: Repository, https://github.com/yourusername/google-pandas-agent.git
Project-URL: Issues, https://github.com/yourusername/google-pandas-agent/issues
Keywords: gemini,pandas,agent,langgraph,google-generativeai,dataframe,analysis
Classifier: Development Status :: 4 - Beta
Classifier: Intended Audience :: Developers
Classifier: Intended Audience :: Science/Research
Classifier: Operating System :: OS Independent
Classifier: Programming Language :: Python :: 3
Classifier: Programming Language :: Python :: 3.10
Classifier: Programming Language :: Python :: 3.11
Classifier: Programming Language :: Python :: 3.12
Classifier: Topic :: Scientific/Engineering :: Artificial Intelligence
Classifier: Topic :: Scientific/Engineering :: Information Analysis
Requires-Python: >=3.10
License-File: LICENSE
Requires-Dist: pandas>=2.2.0
Requires-Dist: google-generativeai>=0.8.5
Requires-Dist: langgraph>=0.3.21
Requires-Dist: typing-extensions>=4.9.0
Provides-Extra: dev
Requires-Dist: pytest>=7.0; extra == "dev"
Requires-Dist: black>=23.0; extra == "dev"
Requires-Dist: isort>=5.0; extra == "dev"
Requires-Dist: mypy>=1.0; extra == "dev"
Requires-Dist: ruff>=0.1.0; extra == "dev"
Provides-Extra: all
Requires-Dist: numpy>=1.24.0; extra == "all"
Requires-Dist: matplotlib>=3.7.0; extra == "all"
Requires-Dist: seaborn>=0.12.0; extra == "all"
Dynamic: license-file
